mat_similarity-0.1rc3.dist-info/licenses/LICENCE
matsimilarity/LICENSE
matsimilarity/README.md
matsimilarity/__init__.py
matsimilarity/core/SimilarityMeasure.py
matsimilarity/core/__init__.py
matsimilarity/core/utils.py
matsimilarity/methods/__init__.py
matsimilarity/methods/mat/__init__.py
matsimilarity/methods/mat/EDR/EDR_T2T.py
matsimilarity/methods/mat/EDR/__init__.py
matsimilarity/methods/mat/LCSS/LCSS_T2T.py
matsimilarity/methods/mat/MSM/MSM_T2T.py
matsimilarity/methods/mat/MUITAS/MUITAS_T2T.py
matsimilarity/methods/mat/MUITAS/__init__.py
mat_similarity-0.1rc3.dist-info/METADATA
mat_similarity-0.1rc3.dist-info/WHEEL
mat_similarity-0.1rc3.dist-info/top_level.txt
mat_similarity-0.1rc3.dist-info/RECORD
