Metadata-Version: 2.4
Name: mat-similarity
Version: 0.1rc3
Summary: Similarity Methods and Functions for Multiple Aspect Trajectory Data Mining
Home-page: https://github.com/mat-analysis/mat-similarity
Author: Vanessa Lago Machado
Author-email: Vanessa Lago Machado <vanessalagomachado@gmail.com>, Tarlis Tortelli Portela <tarlis@tarlis.com.br>
Maintainer-email: Tarlis Tortelli Portela <tarlis@tarlis.com.br>, Vanessa Lago Machado <vanessalagomachado@gmail.com>
License: GPL Version 3 or superior (see LICENSE file)
Project-URL: Homepage, https://github.com/mat-analysis/mat-similarity
Project-URL: Repository, https://github.com/mat-analysis/mat-similarity
Project-URL: Documentation, https://mat-analysis.github.io/mat-tools/mat-similarity/index.html
Project-URL: Download, https://pypi.org/project/mat-similarity/#files
Project-URL: Bug Tracker, https://github.com/mat-analysis/mat-similarity/issues
Keywords: data-science,machine-learning,data-mining,trajectory,multiple-trajectory,similarity
Classifier: Intended Audience :: Science/Research
Classifier: Intended Audience :: Developers
Classifier: License :: OSI Approved :: GNU General Public License v3 or later (GPLv3+)
Classifier: Programming Language :: Python
Classifier: Topic :: Software Development
Classifier: Topic :: Scientific/Engineering
Classifier: Topic :: Scientific/Engineering :: Artificial Intelligence
Classifier: Topic :: Scientific/Engineering :: Information Analysis
Classifier: Topic :: Scientific/Engineering :: Visualization
Classifier: Operating System :: OS Independent
Classifier: Operating System :: Microsoft :: Windows
Classifier: Operating System :: POSIX
Classifier: Operating System :: Unix
Classifier: Operating System :: MacOS
Classifier: Programming Language :: Python :: 3.10
Requires-Python: >=3.7
License-File: LICENCE
Requires-Dist: glob2==0.7
Requires-Dist: numpy
Requires-Dist: pandas
Requires-Dist: mat-data
Requires-Dist: mat-model
Provides-Extra: dev
Requires-Dist: pre-commit; extra == "dev"
Requires-Dist: pytest; extra == "dev"
Requires-Dist: pytest-cov; extra == "dev"
Requires-Dist: pytest-xdist; extra == "dev"
Requires-Dist: wheel; extra == "dev"
Provides-Extra: binder
Requires-Dist: jupyter; extra == "binder"
Provides-Extra: docs
Requires-Dist: jupyter; extra == "docs"
Requires-Dist: numpydoc; extra == "docs"
Provides-Extra: dl
Dynamic: author
Dynamic: home-page
Dynamic: license-file
